sql_mock/__init__.py
sql_mock/bigquery/__init__.py
sql_mock/bigquery/column_mocks.py
sql_mock/bigquery/settings.py
sql_mock/bigquery/table_mocks.py
sql_mock/clickhouse/__init__.py
sql_mock/clickhouse/column_mocks.py
sql_mock/clickhouse/settings.py
sql_mock/clickhouse/table_mocks.py
sql_mock/column_mocks.py
sql_mock/config.py
sql_mock/constants.py
sql_mock/dbt.py
sql_mock/exceptions.py
sql_mock/helpers.py
sql_mock/redshift/__init__.py
sql_mock/redshift/column_mocks.py
sql_mock/redshift/settings.py
sql_mock/redshift/table_mocks.py
sql_mock/snowflake/__init__.py
sql_mock/snowflake/column_mocks.py
sql_mock/snowflake/settings.py
sql_mock/snowflake/table_mocks.py
sql_mock/table_mocks.py
sql_mock-0.6.2.dist-info/METADATA
sql_mock-0.6.2.dist-info/WHEEL
sql_mock-0.6.2.dist-info/RECORD
