Metadata-Version: 2.1
Name: sql-mock
Version: 0.6.2
Summary: Simplify the testing of SQL data models and queries by allowing users to mock input data and create tests for various scenarios. It provides a consistent and convenient way to test the execution of your query without the need to process a massive amount of data.
Home-page: https://github.com/DeepLcom/sql-mock
License: MIT
Author: DeepL SE
Requires-Python: >=3.9,<4.0
Classifier: Development Status :: 4 - Beta
Classifier: Intended Audience :: Developers
Classifier: Intended Audience :: Science/Research
Classifier: License :: OSI Approved :: MIT License
Classifier: Operating System :: OS Independent
Classifier: Programming Language :: Python
Classifier: Programming Language :: Python :: 3
Classifier: Programming Language :: Python :: 3.9
Classifier: Programming Language :: Python :: 3.10
Classifier: Programming Language :: Python :: 3.11
Classifier: Programming Language :: Python :: 3.12
Classifier: Programming Language :: Python :: 3.13
Classifier: Topic :: Database
Classifier: Topic :: Scientific/Engineering
Classifier: Topic :: Software Development
Classifier: Topic :: Software Development :: Libraries
Classifier: Topic :: Software Development :: Libraries :: Python Modules
Classifier: Topic :: Utilities
Provides-Extra: bigquery
Provides-Extra: clickhouse
Provides-Extra: redshift
Provides-Extra: snowflake
Requires-Dist: boto3 (==1.34.14) ; extra == "redshift"
Requires-Dist: clickhouse-connect (>=0.7.0,<0.8.0) ; extra == "clickhouse"
Requires-Dist: google-cloud-bigquery (>=3.11.4,<4.0.0) ; extra == "bigquery"
Requires-Dist: jinja2 (>=3.1.2,<4.0.0)
Requires-Dist: pydantic-settings (>=2.0.3,<3.0.0)
Requires-Dist: pyyaml (>=6.0.1,<7.0.0)
Requires-Dist: redshift-connector (>=2.0.918,<3.0.0) ; extra == "redshift"
Requires-Dist: snowflake-connector-python (>=3.6.0,<4.0.0) ; extra == "snowflake"
Requires-Dist: sqlglot (>=20.5.0,<21.0.0)
Project-URL: Bug Tracker, https://github.com/DeepLcom/sql-mock/issues
Project-URL: Changelog, https://github.com/DeepLcom/sql-mock/blob/main/CHANGELOG.md
Project-URL: Repository, https://github.com/DeepLcom/sql-mock
